[
	{
		"id": "1",
		"stockName": ["台積電","2330"],
		"quantity":"200",
		"leverage":"3",
		"amount": "0",
		"rate": "6",
		"charge": "1,200,000"
	},
	{
		"id": "2",
		"stockName": ["創惟","6104"],
		"quantity":"555",
		"leverage":"3",
		"amount": "0",
		"rate": "3",
		"charge": "1,200,000"
	},
	{
		"id": "3",
		"stockName": ["富喬","1815"],
		"quantity":"300",
		"leverage":"3",
		"amount": "0",
		"rate": "5",
		"charge": "1,200,000"
	},
	{
		"id": "4",
		"stockName": ["美時","1795"],
		"quantity":"300",
		"leverage":"5",
		"amount": "0",
		"rate": "2.5",
		"charge": "1,200,000"
	},
	{
		"id": "5",
		"stockName": ["鴻海","2317"],
		"quantity":"300",
		"leverage":"3",
		"amount": "0",
		"rate": "4",
		"charge": "1,200,000"
	},
	{
		"id": "6",
		"stockName": ["大立光","3008"],
		"quantity":"300",
		"leverage":"6",
		"amount": "0",
		"rate": "2.5",
		"charge": "1,200,000"
	},
	{
		"id": "7",
		"stockName": ["十銓","4967"],
		"quantity":"300",
		"leverage":"2",
		"amount": "0",
		"rate": "2",
		"charge": "465,838"
	},
	{
		"id": "8",
		"stockName": ["益登","3048"],
		"quantity":"104",
		"leverage":"5",
		"amount": "0",
		"rate": "3",
		"charge": "1,200,000"
	},
	{
		"id": "9",
		"stockName": ["錸寶","8104"],
		"quantity":"100",
		"leverage":"5",
		"amount": "0",
		"rate": "3",
		"charge": "2,364,758"
	},
	{
		"id": "10",
		"stockName": ["弘憶股","3312"],
		"quantity":"555",
		"leverage":"6",
		"amount": "0",
		"rate": "1.5",
		"charge": "789,065"
	}
]